BigFlowPrototypes/DataAnalytics.py
BigFlowPrototypes/Image.py
BigFlowPrototypes/Linear.py
BigFlowPrototypes/Linear_Embeded.py
BigFlowPrototypes/__init__.py
BigFlowPrototypes-0.1.dist-info/METADATA
BigFlowPrototypes-0.1.dist-info/WHEEL
BigFlowPrototypes-0.1.dist-info/top_level.txt
BigFlowPrototypes-0.1.dist-info/RECORD
