Metadata-Version: 2.1
Name: BigFlowPrototypes
Version: 0.1
Summary: A package for preprocessing data for AI models
Home-page: https://github.com/yourusername/BigFlowPrototypes
Author: Your Name
Author-email: your_email@example.com
Classifier: Programming Language :: Python :: 3
Classifier: License :: OSI Approved :: MIT License
Classifier: Operating System :: OS Independent
Requires-Python: >=3.6
Requires-Dist: pandas
Requires-Dist: numpy
Requires-Dist: scikit-learn
Requires-Dist: openai
Requires-Dist: python-dotenv
Requires-Dist: scipy
Requires-Dist: tensorflow
